RoboBricks/__init__.py
RoboBricks/constants_lib.py
RoboBricks/main.py
RoboBricks-0.2.4.1.dist-info/LICENSE
RoboBricks-0.2.4.1.dist-info/METADATA
RoboBricks-0.2.4.1.dist-info/WHEEL
RoboBricks-0.2.4.1.dist-info/top_level.txt
RoboBricks-0.2.4.1.dist-info/RECORD
