Metadata-Version: 2.1
Name: RoboBricks
Version: 0.2.4.1
Summary: A Python module for accessing the RoboBricks.
Home-page: UNKNOWN
Author: k.s.corp
Author-email: 
License: UNKNOWN
Keywords: RoboBricks
Platform: UNKNOWN
Classifier: License :: OSI Approved :: MIT License
Classifier: Topic :: Software Development :: Libraries
Classifier: Programming Language :: Python :: 3
Classifier: Operating System :: OS Independent
Requires-Python: >=3.8
